pearson3curve-1.0.0.post0.dist-info/METADATA
pearson3curve-1.0.0.post0.dist-info/WHEEL
pearson3curve-1.0.0.post0.dist-info/licenses/LICENSE
pearson3curve/__init__.py
pearson3curve/curve.py
pearson3curve/data.py
pearson3curve/fitting.py
pearson3curve/pgfplot.py
pearson3curve/plot.py
pearson3curve/py.typed
pearson3curve-1.0.0.post0.dist-info/RECORD
