Metadata-Version: 2.1
Name: pearson3curve
Version: 1.0.0.post0
Summary: Pearson III curve fitting and plotting
Author-Email: ListLee <list.lee@outlook.com>
License: MIT
Project-URL: Homepage, https://github.com/tanukihee/pearson3curve
Project-URL: Documentation, https://github.com/tanukihee/pearson3curve/blob/main/docs/api.md
Project-URL: Repository, https://github.com/tanukihee/pearson3curve.git
Project-URL: Issues, https://github.com/tanukihee/pearson3curve/issues
Requires-Python: >=3.9
Requires-Dist: numpy>=1.26.4
Requires-Dist: scipy>=1.12.0
Requires-Dist: matplotlib>=3.8.3
Requires-Dist: probscale>=0.2.5
